i3_swallow/__init__.py
i3_swallow/swallow.py
i3_swallow-1.0.0.dist-info/entry_points.txt
i3_swallow-1.0.0.dist-info/LICENSE
i3_swallow-1.0.0.dist-info/WHEEL
i3_swallow-1.0.0.dist-info/METADATA
i3_swallow-1.0.0.dist-info/RECORD
