Metadata-Version: 2.1
Name: i3-swallow
Version: 1.0.0
Summary: Swallow a terminal window in i3/sway
Home-page: https://github.com/ViliamV/i3-swallow
License: MIT
Author: jamesofarrell
Requires-Python: >=3.7,<4.0
Classifier: License :: OSI Approved :: MIT License
Classifier: Programming Language :: Python :: 3
Classifier: Programming Language :: Python :: 3.7
Classifier: Programming Language :: Python :: 3.8
Classifier: Programming Language :: Python :: 3.9
Requires-Dist: i3ipc (>=2.2.1,<3.0.0)
Project-URL: Repository, https://github.com/ViliamV/i3-swallow
